{
  "minggu_ini": {
    "tanggal": "Minggu, 8 Juni 2025",
    "peringatan": "Hari Raya Pentakosta",
    "warna": "Hijau",
    "bacaan1": "Kis. 2:1-11",
    "bacaan2": "1 Kor. 12:3b-7.12-13",
    "mazmur": "Mzm. 104",
    "injil": "Yoh. 20:19-23",
    "renungan": "GEREJA YANG DIUTUS : Pada hari kebangkitan-Nya, Yesus menampakkan diri kepada para murid yang sedang bersembunyi karena ketakutan. Ia tidak datang dengan teguran, melainkan dengan sapaan yang menguatkan: “Damai sejahtera bagi kamu.” Sapaan ini Ia ulangi tiga kali, menandakan betapa pentingnya damai itu bagi kehidupan mereka — dan bagi gereja di sepanjang zaman.Namun damai itu bukanlah akhir dari segalanya — itu adalah awal dari perutusan. Setelah memberikan damai, Yesus bersabda: “Sama seperti Bapa mengutus Aku, demikian juga sekarang Aku mengutus kamu.” Gereja tidak dipanggil untuk hanya berkumpul dan merasa nyaman; gereja diutus untuk keluar, menjadi tanda kasih, pengampunan, dan harapan bagi dunia.Yesus kemudian meniupkan Roh Kudus kepada para murid. Ini adalah momen kelahiran gereja diberi kuasa untuk melayani dalam semangat Kristus. Melalui Roh Kudus, gereja menerima otoritas ilahi: untuk mengampuni, untuk menyembuhkan, untuk membawa damai, dan untuk menjadi terang di tengah dunia."
  },
  "minggu_depan": {
    "tanggal": "Minggu, 15 Juni 2025",
    "peringatan": "Hari Raya Tritunggal MahaKudus",
    "warna": "Hijau",
    "bacaan1": "Ams. 8:22-31",
    "bacaan2": "Rm. 5:1-5",
    "mazmur": "Mzm. 159",
    "injil": "Yoh. 16:12-15",
    "renungan": "Pujian, Hormat dan Kemuliaan Bagi Allah Tritunggal."
  }
}